{
  "namespaces": [
    "public"
  ],
  "name": "public",
  "tables": [
    {
      "columns": {
        "id": {
          "name": "id",
          "type": "text",
          "unsigned": false,
          "autoincrement": false,
          "primary": true,
          "nullable": false,
          "unique": false,
          "length": null,
          "precision": null,
          "scale": null,
          "default": null,
          "comment": null,
          "enumItems": [],
          "mappedType": "text"
        },
        "actor_id": {
          "name": "actor_id",
          "type": "text",
          "unsigned": false,
          "autoincrement": false,
          "primary": false,
          "nullable": true,
          "unique": false,
          "length": null,
          "precision": null,
          "scale": null,
          "default": null,
          "comment": null,
          "enumItems": [],
          "mappedType": "text"
        },
        "actor_type": {
          "name": "actor_type",
          "type": "text",
          "unsigned": false,
          "autoincrement": false,
          "primary": false,
          "nullable": false,
          "unique": false,
          "length": null,
          "precision": null,
          "scale": null,
          "default": null,
          "comment": null,
          "enumItems": [],
          "mappedType": "text"
        },
        "action": {
          "name": "action",
          "type": "text",
          "unsigned": false,
          "autoincrement": false,
          "primary": false,
          "nullable": false,
          "unique": false,
          "length": null,
          "precision": null,
          "scale": null,
          "default": null,
          "comment": null,
          "enumItems": [],
          "mappedType": "text"
        },
        "entity": {
          "name": "entity",
          "type": "text",
          "unsigned": false,
          "autoincrement": false,
          "primary": false,
          "nullable": false,
          "unique": false,
          "length": null,
          "precision": null,
          "scale": null,
          "default": null,
          "comment": null,
          "enumItems": [],
          "mappedType": "text"
        },
        "entity_id": {
          "name": "entity_id",
          "type": "text",
          "unsigned": false,
          "autoincrement": false,
          "primary": false,
          "nullable": true,
          "unique": false,
          "length": null,
          "precision": null,
          "scale": null,
          "default": null,
          "comment": null,
          "enumItems": [],
          "mappedType": "text"
        },
        "metadata": {
          "name": "metadata",
          "type": "jsonb",
          "unsigned": false,
          "autoincrement": false,
          "primary": false,
          "nullable": true,
          "unique": false,
          "length": null,
          "precision": null,
          "scale": null,
          "default": null,
          "comment": null,
          "enumItems": [],
          "mappedType": "json"
        },
        "created_at": {
          "name": "created_at",
          "type": "timestamptz",
          "unsigned": false,
          "autoincrement": false,
          "primary": false,
          "nullable": false,
          "unique": false,
          "length": 6,
          "precision": null,
          "scale": null,
          "default": "now()",
          "comment": null,
          "enumItems": [],
          "mappedType": "datetime"
        },
        "updated_at": {
          "name": "updated_at",
          "type": "timestamptz",
          "unsigned": false,
          "autoincrement": false,
          "primary": false,
          "nullable": false,
          "unique": false,
          "length": 6,
          "precision": null,
          "scale": null,
          "default": "now()",
          "comment": null,
          "enumItems": [],
          "mappedType": "datetime"
        },
        "deleted_at": {
          "name": "deleted_at",
          "type": "timestamptz",
          "unsigned": false,
          "autoincrement": false,
          "primary": false,
          "nullable": true,
          "unique": false,
          "length": 6,
          "precision": null,
          "scale": null,
          "default": null,
          "comment": null,
          "enumItems": [],
          "mappedType": "datetime"
        }
      },
      "name": "audit_log",
      "schema": "public",
      "indexes": [
        {
          "keyName": "IDX_audit_log_deleted_at",
          "columnNames": [],
          "composite": false,
          "constraint": false,
          "primary": false,
          "unique": false,
          "expression": "CREATE INDEX IF NOT EXISTS \"IDX_audit_log_deleted_at\" ON \"audit_log\" (\"deleted_at\") WHERE deleted_at IS NULL"
        },
        {
          "keyName": "audit_log_pkey",
          "columnNames": [
            "id"
          ],
          "composite": false,
          "constraint": true,
          "primary": true,
          "unique": true
        }
      ],
      "checks": [],
      "foreignKeys": {},
      "nativeEnums": {}
    }
  ],
  "nativeEnums": {}
}
